pyERGM/__init__.py
pyERGM/cluster_utils.py
pyERGM/datasets.py
pyERGM/ergm.py
pyERGM/metrics.py
pyERGM/mple_optimizaiton.py
pyERGM/sampling.py
pyERGM/utils.py
pyergm-0.2.8.dist-info/METADATA
pyergm-0.2.8.dist-info/WHEEL
pyergm-0.2.8.dist-info/top_level.txt
pyergm-0.2.8.dist-info/RECORD
