Metadata-Version: 2.4
Name: pyERGM
Version: 0.2.8
Summary: Exponential Random Graph Models in Python
Home-page: https://github.com/tomtalp/pyERGM
Requires-Python: >=3.10
Dynamic: description
Dynamic: description-content-type
Dynamic: home-page
Dynamic: requires-python
Dynamic: summary
